lsdpiptest/__init__.py
lsdpiptest/testCode.py
lsdpiptest-0.0.1.dist-info/METADATA
lsdpiptest-0.0.1.dist-info/WHEEL
lsdpiptest-0.0.1.dist-info/top_level.txt
lsdpiptest-0.0.1.dist-info/RECORD
